pycrmod.cpython-312-arm-linux-gnueabihf.so
pycrtomo.cpython-312-arm-linux-gnueabihf.so
pycutmck.cpython-312-arm-linux-gnueabihf.so
pycrtomomod-0.0.10.data/purelib/crtomo_tests/__init__.py
pycrtomomod-0.0.10.data/purelib/crtomo_tests/extract_pyinv_examples.py
pycrtomomod-0.0.10.data/purelib/crtomo_tests/pycrtomo.py
pycrtomomod-0.0.10.data/purelib/crtomo_tests/data/example_inversion_01.zip
pycrtomomod-0.0.10.data/purelib/crtomo_tests/data/example_modeling_01.zip
pycrtomomod-0.0.10.data/purelib/crtomo_wrapper/__init__.py
pycrtomomod-0.0.10.data/purelib/crtomo_wrapper/crmod.py
pycrtomomod-0.0.10.data/purelib/crtomo_wrapper/crtomo.py
pycrtomomod-0.0.10.data/purelib/crtomo_wrapper/cutmckee.py
pycrtomomod.libs/libgfortran-947613b6.so.5.0.0
pycrtomomod.libs/libgomp-39027b09.so.1.0.0
pycrtomomod-0.0.10.dist-info/METADATA
pycrtomomod-0.0.10.dist-info/WHEEL
pycrtomomod-0.0.10.dist-info/entry_points.txt
pycrtomomod-0.0.10.dist-info/RECORD
