Metadata-Version: 2.1
Name: pycrtomomod
Version: 0.0.10
Summary: Python-wrapper modules for CRMod, CRTomo, CutMcK. Original code by Andreas Kemna.
Author-Email: Andreas Kemna <kemna@geo.uni-bonn.de>, Maximilian Weigand <mweigand@geo.uni-bonn.de>, "Geophysics Section, University of Bonn, Germany" <kemna@geo.uni-bonn.de>
Requires-Python: >=3.8
Requires-Dist: numpy
